{
  "CO1" : {
    "QUANTITY": 2,
    "TYPE": "equals",
    "POSITION" : [
      [2,2],
      [2,3],
      [3,2],
      [3,3]
    ]
  },
  "CO2" : {
    "QUANTITY": 2,
    "TYPE": "different",
    "POSITION" : [
      [0,2],
      [1,2],
      [2,2],
      [3,2],
      [4,2],
      [5,2]
    ]
  },
  "CO3" : {
    "QUANTITY": 4,
    "TYPE": "equals",
    "POSITION" : [
      [1,2],
      [2,2],
      [3,2],
      [4,2]
    ]
  },
  "CO4" : {
    "QUANTITY": 6,
    "TYPE": "equals",
    "POSITION" : [
      [2,2],
      [3,2]
    ]
  },
  "CO5" : {
    "QUANTITY": 3,
    "TYPE": "max3",
    "POSITION" : [
      [0,2],
      [1,2],
      [2,2],
      [3,2],
      [4,2],
      [5,2]
    ]
  },
  "CO6" : {
    "QUANTITY": 2,
    "TYPE": "different",
    "POSITION" : [
      [2,0],
      [2,1],
      [2,2],
      [2,3],
      [2,4]
    ]
  },
  "CO7" : {
    "QUANTITY": 4,
    "TYPE": "max3",
    "POSITION" : [
      [2,0],
      [2,1],
      [2,2],
      [2,3],
      [2,4]
    ]
  },
  "CO8" : {
    "QUANTITY": 1,
    "TYPE": "equals",
    "POSITION" : [
      [0,0],
      [5,0],
      [0,4],
      [5,4]
    ]
  },
  "CO9" : {
    "QUANTITY": 1,
    "TYPE": "equals",
    "POSITION" : [
      [5,0],
      [5,2],
      [5,4],
      [3,0],
      [3,2],
      [3,4],
      [1,1],
      [1,3]
    ]
  },
  "CO10" : {
    "QUANTITY": 1,
    "TYPE": "equals",
    "POSITION" : [
      [2,1],
      [2,3],
      [3,2],
      [4,1],
      [4,3]
    ]
  },
  "CO11" : {
    "QUANTITY": 1,
    "TYPE": "equals",
    "POSITION" : [
      [0,0],
      [1,1],
      [2,2],
      [3,3],
      [4,4]
    ]
  },
  "CO12" : {
    "QUANTITY": 1,
    "TYPE": "notimportant",
    "POSITION" : [
      [1,0],
      [2,0],
      [3,0],
      [4,0],
      [5,0],
      [2,1],
      [3,1],
      [4,1],
      [5,1],
      [3,2],
      [4,2],
      [5,2],
      [4,3],
      [5,3],
      [5,4]
    ]
  }
}
